node/__init__.py
node/node.py
node/core/__init__.py
node/core/main.py
node/core/node.py
node_core-1.3.3.dist-info/LICENSE
node_core-1.3.3.dist-info/METADATA
node_core-1.3.3.dist-info/WHEEL
node_core-1.3.3.dist-info/top_level.txt
node_core-1.3.3.dist-info/RECORD
