Metadata-Version: 2.1
Name: node-core
Version: 1.3.3
Summary: UNKNOWN
Home-page: UNKNOWN
Author: Kilthunox
License: UNKNOWN
Platform: UNKNOWN
Classifier: Programming Language :: Python :: 3
License-File: LICENSE
